led/led.v
module top (
    input wire clk,   // onboard clock
    output reg led    // LED output
);

    reg [24:0] counter = 0;  // large counter for delay

    always @(posedge clk) begin
        counter <= counter + 1;
        led <= counter[3];   // toggle LED slowly
    end

endmodule

tb.v
`timescale 1ns/1ps

module tb;

reg clk = 0;
wire led;

// Instantiate DUT
top uut (
    .clk(clk),
    .led(led)
);

/////////////////////////////////////////////////
// CLOCK GENERATION (VERY IMPORTANT)
/////////////////////////////////////////////////
always #5 clk = ~clk;   // 10ns clock period

/////////////////////////////////////////////////
// SIMULATION CONTROL
/////////////////////////////////////////////////
initial begin
    $dumpfile("wave.vcd");
    $dumpvars(0, tb);

    #2000;   // run long enough
    $finish;
end

endmodule

led/wave.vcd
$date
	Thu Apr  9 11:38:01 2026
$end
$version
	Icarus Verilog
$end
$timescale
	1ps
$end
$scope module tb $end
$var wire 1 ! led $end
$var reg 1 " clk $end
$scope module uut $end
$var wire 1 " clk $end
$var reg 25 # counter [24:0] $end
$var reg 1 ! led $end
$upscope $end
$upscope $end
$enddefinitions $end
$comment Show the parameter values. $end
$dumpall
$end
#0
$dumpvars
b0 #
0"
x!
$end
#5000
0!
b1 #
1"
#10000
0"
#15000
b10 #
1"
#20000
0"
#25000
b11 #
1"
#30000
0"
#35000
b100 #
1"
#40000
0"
#45000
b101 #
1"
#50000
0"
#55000
b110 #
1"
#60000
0"
#65000
b111 #
1"
#70000
0"
#75000
b1000 #
1"
#80000
0"
#85000
1!
b1001 #
1"
#90000
0"
#95000
b1010 #
1"
#100000
0"
#105000
b1011 #
1"
#110000
0"
#115000
b1100 #
1"
#120000
0"
#125000
b1101 #
1"
#130000
0"
#135000
b1110 #
1"
#140000
0"
#145000
b1111 #
1"
#150000
0"
#155000
b10000 #
1"
#160000
0"
#165000
0!
b10001 #
1"
#170000
0"
#175000
b10010 #
1"
#180000
0"
#185000
b10011 #
1"
#190000
0"
#195000
b10100 #
1"
#200000
0"
#205000
b10101 #
1"
#210000
0"
#215000
b10110 #
1"
#220000
0"
#225000
b10111 #
1"
#230000
0"
#235000
b11000 #
1"
#240000
0"
#245000
1!
b11001 #
1"
#250000
0"
#255000
b11010 #
1"
#260000
0"
#265000
b11011 #
1"
#270000
0"
#275000
b11100 #
1"
#280000
0"
#285000
b11101 #
1"
#290000
0"
#295000
b11110 #
1"
#300000
0"
#305000
b11111 #
1"
#310000
0"
#315000
b100000 #
1"
#320000
0"
#325000
0!
b100001 #
1"
#330000
0"
#335000
b100010 #
1"
#340000
0"
#345000
b100011 #
1"
#350000
0"
#355000
b100100 #
1"
#360000
0"
#365000
b100101 #
1"
#370000
0"
#375000
b100110 #
1"
#380000
0"
#385000
b100111 #
1"
#390000
0"
#395000
b101000 #
1"
#400000
0"
#405000
1!
b101001 #
1"
#410000
0"
#415000
b101010 #
1"
#420000
0"
#425000
b101011 #
1"
#430000
0"
#435000
b101100 #
1"
#440000
0"
#445000
b101101 #
1"
#450000
0"
#455000
b101110 #
1"
#460000
0"
#465000
b101111 #
1"
#470000
0"
#475000
b110000 #
1"
#480000
0"
#485000
0!
b110001 #
1"
#490000
0"
#495000
b110010 #
1"
#500000
0"
#505000
b110011 #
1"
#510000
0"
#515000
b110100 #
1"
#520000
0"
#525000
b110101 #
1"
#530000
0"
#535000
b110110 #
1"
#540000
0"
#545000
b110111 #
1"
#550000
0"
#555000
b111000 #
1"
#560000
0"
#565000
1!
b111001 #
1"
#570000
0"
#575000
b111010 #
1"
#580000
0"
#585000
b111011 #
1"
#590000
0"
#595000
b111100 #
1"
#600000
0"
#605000
b111101 #
1"
#610000
0"
#615000
b111110 #
1"
#620000
0"
#625000
b111111 #
1"
#630000
0"
#635000
b1000000 #
1"
#640000
0"
#645000
0!
b1000001 #
1"
#650000
0"
#655000
b1000010 #
1"
#660000
0"
#665000
b1000011 #
1"
#670000
0"
#675000
b1000100 #
1"
#680000
0"
#685000
b1000101 #
1"
#690000
0"
#695000
b1000110 #
1"
#700000
0"
#705000
b1000111 #
1"
#710000
0"
#715000
b1001000 #
1"
#720000
0"
#725000
1!
b1001001 #
1"
#730000
0"
#735000
b1001010 #
1"
#740000
0"
#745000
b1001011 #
1"
#750000
0"
#755000
b1001100 #
1"
#760000
0"
#765000
b1001101 #
1"
#770000
0"
#775000
b1001110 #
1"
#780000
0"
#785000
b1001111 #
1"
#790000
0"
#795000
b1010000 #
1"
#800000
0"
#805000
0!
b1010001 #
1"
#810000
0"
#815000
b1010010 #
1"
#820000
0"
#825000
b1010011 #
1"
#830000
0"
#835000
b1010100 #
1"
#840000
0"
#845000
b1010101 #
1"
#850000
0"
#855000
b1010110 #
1"
#860000
0"
#865000
b1010111 #
1"
#870000
0"
#875000
b1011000 #
1"
#880000
0"
#885000
1!
b1011001 #
1"
#890000
0"
#895000
b1011010 #
1"
#900000
0"
#905000
b1011011 #
1"
#910000
0"
#915000
b1011100 #
1"
#920000
0"
#925000
b1011101 #
1"
#930000
0"
#935000
b1011110 #
1"
#940000
0"
#945000
b1011111 #
1"
#950000
0"
#955000
b1100000 #
1"
#960000
0"
#965000
0!
b1100001 #
1"
#970000
0"
#975000
b1100010 #
1"
#980000
0"
#985000
b1100011 #
1"
#990000
0"
#995000
b1100100 #
1"
